labl/__init__.py
labl/commands/cli.py
labl/data/__init__.py
labl/data/base_entry.py
labl/data/base_sequence.py
labl/data/edited_dataset.py
labl/data/edited_entry.py
labl/data/labeled_dataset.py
labl/data/labeled_entry.py
labl/data/labeled_interface.py
labl/datasets/__init__.py
labl/datasets/translation/__init__.py
labl/datasets/translation/divemt.py
labl/datasets/translation/qe4pe.py
labl/datasets/translation/wmt24_esa.py
labl/utils/__init__.py
labl/utils/aggregation.py
labl/utils/agreement.py
labl/utils/cache.py
labl/utils/jiwer_ext.py
labl/utils/span.py
labl/utils/token.py
labl/utils/tokenizer.py
labl/utils/transform.py
labl/utils/typing.py
labl-0.1.1.dist-info/licenses/LICENSE
labl-0.1.1.dist-info/METADATA
labl-0.1.1.dist-info/WHEEL
labl-0.1.1.dist-info/entry_points.txt
labl-0.1.1.dist-info/top_level.txt
labl-0.1.1.dist-info/RECORD
