Metadata-Version: 2.4
Name: labl
Version: 0.1.1
Summary: Word-level Quality Estimation Toolkit
Author-email: Gabriele Sarti <gabriele.sarti996@gmail.com>, Vilém Zouhar <vilem.zouhar@gmail.com>
Maintainer-email: Gabriele Sarti <gabriele.sarti996@gmail.com>
License: Apache License
Project-URL: homepage, https://github.com/gsarti/labl
Project-URL: documentation, https://github.com/gsarti/labl
Project-URL: repository, https://github.com/gsarti/labl
Project-URL: changelog, https://github.com/gsarti/labl/blob/main/CHANGELOG.md
Keywords: machine translation,quality estimation,natural language processing,interpretability
Classifier: Development Status :: 3 - Alpha
Classifier: Environment :: Console
Classifier: Framework :: Jupyter
Classifier: Intended Audience :: Science/Research
Classifier: Intended Audience :: Developers
Classifier: License :: OSI Approved :: Apache Software License
Classifier: Operating System :: OS Independent
Classifier: Programming Language :: Python
Classifier: Programming Language :: Python :: 3
Classifier: Programming Language :: Python :: 3.10
Classifier: Programming Language :: Python :: 3.11
Classifier: Programming Language :: Python :: 3.12
Classifier: Topic :: Scientific/Engineering :: Visualization
Classifier: Typing :: Typed
Requires-Python: >=3.10
License-File: LICENSE
Requires-Dist: typer>=0.15.2
Requires-Dist: jiwer>=3.1.0
Requires-Dist: transformers>=4.42.0
Requires-Dist: krippendorff>=0.8.1
Requires-Dist: scipy>=1.15.2
Requires-Dist: toml>=0.10.2
Provides-Extra: data
Requires-Dist: datasets>=2.4.0; extra == "data"
Requires-Dist: pandas>=1.5.3; extra == "data"
Provides-Extra: docs
Requires-Dist: mkdocs>=1.6.1; extra == "docs"
Requires-Dist: mkdocs-material>=9.5.34; extra == "docs"
Requires-Dist: mkdocs-autorefs>=1.1.0; extra == "docs"
Requires-Dist: mkdocs-section-index>=0.3.9; extra == "docs"
Requires-Dist: mkdocstrings>=0.25.2; extra == "docs"
Requires-Dist: mkdocstrings-python>=1.10.9; extra == "docs"
Requires-Dist: mknotebooks>=0.8.0; extra == "docs"
Requires-Dist: docstr-coverage>=2.3.2; extra == "docs"
Provides-Extra: lint
Requires-Dist: pre-commit>=4.2.0; extra == "lint"
Requires-Dist: pytest>=8.3.5; extra == "lint"
Requires-Dist: pytest-xdist>=3.6.1; extra == "lint"
Requires-Dist: ruff>=0.11.0; extra == "lint"
Provides-Extra: notebook
Requires-Dist: ipykernel>=6.29.5; extra == "notebook"
Requires-Dist: ipywidgets>=8.1.5; extra == "notebook"
Dynamic: license-file
